linebreaker/__init__.py
linebreaker/_version.py
linebreaker/cli.py
linebreaker/core.py
linebreaker-0.0.0.dist-info/licenses/LICENSE
linebreaker-0.0.0.dist-info/METADATA
linebreaker-0.0.0.dist-info/WHEEL
linebreaker-0.0.0.dist-info/entry_points.txt
linebreaker-0.0.0.dist-info/top_level.txt
linebreaker-0.0.0.dist-info/RECORD
