Metadata-Version: 2.4
Name: linebreaker
Version: 0.0.0
Summary: Intelligent line breaking for Markdown and text files
Author-email: Silas Kieser <silas.kieser@gmail.com>
Maintainer-email: Silas Kieser <silas.kieser@gmail.com>
License-Expression: MIT
Project-URL: Homepage, https://github.com/SilasK/linebreaker
Project-URL: Repository, https://github.com/SilasK/linebreaker
Project-URL: Issues, https://github.com/SilasK/linebreaker/issues
Project-URL: Changelog, https://github.com/SilasK/linebreaker/blob/main/CHANGELOG.md
Keywords: markdown,text,line-breaking,formatting
Classifier: Development Status :: 4 - Beta
Classifier: Intended Audience :: Developers
Classifier: Operating System :: OS Independent
Classifier: Programming Language :: Python :: 3
Classifier: Programming Language :: Python :: 3.8
Classifier: Programming Language :: Python :: 3.9
Classifier: Programming Language :: Python :: 3.10
Classifier: Programming Language :: Python :: 3.11
Classifier: Programming Language :: Python :: 3.12
Classifier: Topic :: Text Processing :: Markup :: Markdown
Requires-Python: >=3.8
License-File: LICENSE
Provides-Extra: dev
Requires-Dist: pytest>=7.0; extra == "dev"
Requires-Dist: pytest-cov; extra == "dev"
Requires-Dist: build; extra == "dev"
Requires-Dist: versioneer; extra == "dev"
Dynamic: license-file
